{
  "updated_at": "2026-07-09T20:31:58+09:00",
  "as_of_date": "2026-07-09",
  "ma_period": 50,
  "ma_periods": [
    10,
    20,
    50
  ],
  "slope_lookback": 5,
  "zones": {
    "cooldown_max": 105,
    "normal_max": 120,
    "warning_max": 130
  },
  "indices": [
    {
      "ticker": "KS11",
      "symbol": "^KS11",
      "kind": "index",
      "name_ko": "코스피",
      "name_en": "KOSPI Composite Index",
      "theme": "한국 종합주가지수",
      "price": 7291.91,
      "ma10": 7956.85,
      "ma20": 8333.25,
      "ma50": 7947.36,
      "disparity": 91.75,
      "zone": "cooldown",
      "market": {
        "state": "bear",
        "label": "하락장",
        "score": -78.1,
        "cross": false,
        "up10": false,
        "up20": false,
        "spread_pct": -4.52,
        "slope10_pct": -6.4,
        "slope20_pct": -0.54
      },
      "as_of_date": "2026-07-09"
    },
    {
      "ticker": "KQ11",
      "symbol": "^KQ11",
      "kind": "index",
      "name_ko": "코스닥",
      "name_en": "KOSDAQ Composite Index",
      "theme": "코스닥 종합지수",
      "price": 794.0,
      "ma10": 860.99,
      "ma20": 917.41,
      "ma50": 1037.54,
      "disparity": 76.53,
      "zone": "cooldown",
      "market": {
        "state": "bear",
        "label": "하락장",
        "score": -100.0,
        "cross": false,
        "up10": false,
        "up20": false,
        "spread_pct": -6.15,
        "slope10_pct": -5.47,
        "slope20_pct": -3.7
      },
      "as_of_date": "2026-07-09"
    }
  ],
  "sectors": [
    {
      "ticker": "0008T0",
      "symbol": "0008T0.KS",
      "kind": "sector",
      "name_ko": "K-컬처",
      "name_en": "K-Culture",
      "theme": "SOL 화장품TOP3플러스",
      "price": 14470.0,
      "ma10": 14543.5,
      "ma20": 14107.75,
      "ma50": 14744.4,
      "disparity": 98.14,
      "zone": "cooldown",
      "market": {
        "state": "bull",
        "label": "상승장",
        "score": 100.0,
        "cross": true,
        "up10": true,
        "up20": true,
        "spread_pct": 3.09,
        "slope10_pct": 6.13,
        "slope20_pct": 2.21
      },
      "as_of_date": "2026-07-09",
      "rank": 1
    },
    {
      "ticker": "401470",
      "symbol": "401470.KS",
      "kind": "sector",
      "name_ko": "IT/플랫폼",
      "name_en": "IT / Platform",
      "theme": "KODEX 메타버스액티브",
      "price": 10000.0,
      "ma10": 10188.0,
      "ma20": 10466.0,
      "ma50": 10331.3,
      "disparity": 96.79,
      "zone": "cooldown",
      "market": {
        "state": "bear",
        "label": "하락장",
        "score": -70.9,
        "cross": false,
        "up10": false,
        "up20": false,
        "spread_pct": -2.66,
        "slope10_pct": -1.86,
        "slope20_pct": -0.82
      },
      "as_of_date": "2026-07-09",
      "rank": 2
    },
    {
      "ticker": "395160",
      "symbol": "395160.KS",
      "kind": "sector",
      "name_ko": "반도체",
      "name_en": "Semiconductors",
      "theme": "KODEX AI반도체TOP2플러스",
      "price": 45470.0,
      "ma10": 51917.5,
      "ma20": 54542.25,
      "ma50": 47309.8,
      "disparity": 96.11,
      "zone": "cooldown",
      "market": {
        "state": "bear",
        "label": "하락장",
        "score": -71.2,
        "cross": false,
        "up10": false,
        "up20": false,
        "spread_pct": -4.81,
        "slope10_pct": -10.1,
        "slope20_pct": -0.08
      },
      "as_of_date": "2026-07-09",
      "rank": 3
    },
    {
      "ticker": "472720",
      "symbol": "472720.KS",
      "kind": "sector",
      "name_ko": "금융",
      "name_en": "Financials",
      "theme": "TRUSTON 주주가치액티브",
      "price": 26835.0,
      "ma10": 28535.0,
      "ma20": 29509.5,
      "ma50": 29573.3,
      "disparity": 90.74,
      "zone": "cooldown",
      "market": {
        "state": "bear",
        "label": "하락장",
        "score": -78.1,
        "cross": false,
        "up10": false,
        "up20": false,
        "spread_pct": -3.3,
        "slope10_pct": -3.7,
        "slope20_pct": -0.54
      },
      "as_of_date": "2026-07-09",
      "rank": 4
    },
    {
      "ticker": "261140",
      "symbol": "261140.KS",
      "kind": "sector",
      "name_ko": "국내주식",
      "name_en": "Domestic Equity",
      "theme": "TIGER 우선주",
      "price": 24315.0,
      "ma10": 26470.0,
      "ma20": 27429.25,
      "ma50": 27679.9,
      "disparity": 87.84,
      "zone": "cooldown",
      "market": {
        "state": "bear",
        "label": "하락장",
        "score": -90.0,
        "cross": false,
        "up10": false,
        "up20": false,
        "spread_pct": -3.5,
        "slope10_pct": -4.16,
        "slope20_pct": -1.34
      },
      "as_of_date": "2026-07-09",
      "rank": 5
    },
    {
      "ticker": "407820",
      "symbol": "407820.KS",
      "kind": "sector",
      "name_ko": "소비재",
      "name_en": "Consumer",
      "theme": "에셋플러스 코리아플랫폼액티브",
      "price": 6570.0,
      "ma10": 7059.0,
      "ma20": 7266.25,
      "ma50": 7743.8,
      "disparity": 84.84,
      "zone": "cooldown",
      "market": {
        "state": "bear",
        "label": "하락장",
        "score": -87.4,
        "cross": false,
        "up10": false,
        "up20": false,
        "spread_pct": -2.85,
        "slope10_pct": -3.41,
        "slope20_pct": -1.16
      },
      "as_of_date": "2026-07-09",
      "rank": 6
    },
    {
      "ticker": "139250",
      "symbol": "139250.KS",
      "kind": "sector",
      "name_ko": "화학/소재",
      "name_en": "Chemicals / Materials",
      "theme": "TIGER 200 에너지화학",
      "price": 16385.0,
      "ma10": 17532.5,
      "ma20": 18356.75,
      "ma50": 19404.1,
      "disparity": 84.44,
      "zone": "cooldown",
      "market": {
        "state": "bear",
        "label": "하락장",
        "score": -100.0,
        "cross": false,
        "up10": false,
        "up20": false,
        "spread_pct": -4.49,
        "slope10_pct": -4.32,
        "slope20_pct": -2.11
      },
      "as_of_date": "2026-07-09",
      "rank": 7
    },
    {
      "ticker": "307520",
      "symbol": "307520.KS",
      "kind": "sector",
      "name_ko": "지주사",
      "name_en": "Holding Companies",
      "theme": "TIGER 지주회사",
      "price": 20585.0,
      "ma10": 22353.5,
      "ma20": 23325.75,
      "ma50": 24522.8,
      "disparity": 83.94,
      "zone": "cooldown",
      "market": {
        "state": "bear",
        "label": "하락장",
        "score": -98.1,
        "cross": false,
        "up10": false,
        "up20": false,
        "spread_pct": -4.17,
        "slope10_pct": -3.66,
        "slope20_pct": -1.87
      },
      "as_of_date": "2026-07-09",
      "rank": 8
    },
    {
      "ticker": "381560",
      "symbol": "381560.KS",
      "kind": "sector",
      "name_ko": "자동차",
      "name_en": "Automobiles",
      "theme": "HANARO Fn전기&수소차",
      "price": 16990.0,
      "ma10": 18577.0,
      "ma20": 19995.0,
      "ma50": 20340.5,
      "disparity": 83.53,
      "zone": "cooldown",
      "market": {
        "state": "bear",
        "label": "하락장",
        "score": -100.0,
        "cross": false,
        "up10": false,
        "up20": false,
        "spread_pct": -7.09,
        "slope10_pct": -5.65,
        "slope20_pct": -3.64
      },
      "as_of_date": "2026-07-09",
      "rank": 9
    },
    {
      "ticker": "307510",
      "symbol": "307510.KS",
      "kind": "sector",
      "name_ko": "바이오",
      "name_en": "Bio / Healthcare",
      "theme": "TIGER 의료기기",
      "price": 12985.0,
      "ma10": 13852.0,
      "ma20": 14083.5,
      "ma50": 15557.1,
      "disparity": 83.47,
      "zone": "cooldown",
      "market": {
        "state": "bear",
        "label": "하락장",
        "score": -69.7,
        "cross": false,
        "up10": false,
        "up20": false,
        "spread_pct": -1.64,
        "slope10_pct": -1.15,
        "slope20_pct": -1.69
      },
      "as_of_date": "2026-07-09",
      "rank": 10
    },
    {
      "ticker": "139220",
      "symbol": "139220.KS",
      "kind": "sector",
      "name_ko": "인프라",
      "name_en": "Infrastructure",
      "theme": "TIGER 200 건설",
      "price": 7040.0,
      "ma10": 7827.0,
      "ma20": 8311.75,
      "ma50": 8971.9,
      "disparity": 78.47,
      "zone": "cooldown",
      "market": {
        "state": "bear",
        "label": "하락장",
        "score": -96.5,
        "cross": false,
        "up10": false,
        "up20": false,
        "spread_pct": -5.83,
        "slope10_pct": -4.9,
        "slope20_pct": -1.77
      },
      "as_of_date": "2026-07-09",
      "rank": 11
    },
    {
      "ticker": "455850",
      "symbol": "455850.KS",
      "kind": "sector",
      "name_ko": "AI반도체 소부장",
      "name_en": "AI Semiconductor Materials & Equipment",
      "theme": "SOL AI반도체소부장",
      "price": 23530.0,
      "ma10": 26668.5,
      "ma20": 28850.25,
      "ma50": 29999.3,
      "disparity": 78.44,
      "zone": "cooldown",
      "market": {
        "state": "bear",
        "label": "하락장",
        "score": -100.0,
        "cross": false,
        "up10": false,
        "up20": false,
        "spread_pct": -7.56,
        "slope10_pct": -8.1,
        "slope20_pct": -3.59
      },
      "as_of_date": "2026-07-09",
      "rank": 12
    },
    {
      "ticker": "445290",
      "symbol": "445290.KS",
      "kind": "sector",
      "name_ko": "기계",
      "name_en": "Machinery",
      "theme": "KODEX 로봇액티브",
      "price": 29800.0,
      "ma10": 32540.0,
      "ma20": 35533.5,
      "ma50": 38287.5,
      "disparity": 77.83,
      "zone": "cooldown",
      "market": {
        "state": "bear",
        "label": "하락장",
        "score": -100.0,
        "cross": false,
        "up10": false,
        "up20": false,
        "spread_pct": -8.42,
        "slope10_pct": -7.21,
        "slope20_pct": -5.61
      },
      "as_of_date": "2026-07-09",
      "rank": 13
    },
    {
      "ticker": "449450",
      "symbol": "449450.KS",
      "kind": "sector",
      "name_ko": "방산",
      "name_en": "Defense",
      "theme": "PLUS K방산",
      "price": 52200.0,
      "ma10": 59070.5,
      "ma20": 62490.5,
      "ma50": 67218.9,
      "disparity": 77.66,
      "zone": "cooldown",
      "market": {
        "state": "bear",
        "label": "하락장",
        "score": -75.6,
        "cross": false,
        "up10": false,
        "up20": false,
        "spread_pct": -5.47,
        "slope10_pct": -3.57,
        "slope20_pct": -0.37
      },
      "as_of_date": "2026-07-09",
      "rank": 14
    },
    {
      "ticker": "373490",
      "symbol": "373490.KS",
      "kind": "sector",
      "name_ko": "전력/에너지",
      "name_en": "Power / Energy",
      "theme": "KODEX 코리아혁신성장액티브",
      "price": 24200.0,
      "ma10": 28222.0,
      "ma20": 30309.0,
      "ma50": 31805.0,
      "disparity": 76.09,
      "zone": "cooldown",
      "market": {
        "state": "bear",
        "label": "하락장",
        "score": -100.0,
        "cross": false,
        "up10": false,
        "up20": false,
        "spread_pct": -6.89,
        "slope10_pct": -7.29,
        "slope20_pct": -3.64
      },
      "as_of_date": "2026-07-09",
      "rank": 15
    },
    {
      "ticker": "494670",
      "symbol": "494670.KS",
      "kind": "sector",
      "name_ko": "조선/해운",
      "name_en": "Shipbuilding / Shipping",
      "theme": "TIGER 조선TOP10",
      "price": 21460.0,
      "ma10": 24282.0,
      "ma20": 26157.0,
      "ma50": 28570.6,
      "disparity": 75.11,
      "zone": "cooldown",
      "market": {
        "state": "bear",
        "label": "하락장",
        "score": -100.0,
        "cross": false,
        "up10": false,
        "up20": false,
        "spread_pct": -7.17,
        "slope10_pct": -5.77,
        "slope20_pct": -3.0
      },
      "as_of_date": "2026-07-09",
      "rank": 16
    },
    {
      "ticker": "482030",
      "symbol": "482030.KS",
      "kind": "sector",
      "name_ko": "2차전지",
      "name_en": "Batteries",
      "theme": "KoAct 반도체&2차전지핵심소재액티브",
      "price": 8385.0,
      "ma10": 9501.0,
      "ma20": 10402.5,
      "ma50": 11980.6,
      "disparity": 69.99,
      "zone": "cooldown",
      "market": {
        "state": "bear",
        "label": "하락장",
        "score": -100.0,
        "cross": false,
        "up10": false,
        "up20": false,
        "spread_pct": -8.67,
        "slope10_pct": -8.37,
        "slope20_pct": -4.65
      },
      "as_of_date": "2026-07-09",
      "rank": 17
    }
  ]
}